odoo/addons/product_uom_measure_type/README.rst
odoo/addons/product_uom_measure_type/__init__.py
odoo/addons/product_uom_measure_type/__manifest__.py
odoo/addons/product_uom_measure_type/hooks.py
odoo/addons/product_uom_measure_type/i18n/es.po
odoo/addons/product_uom_measure_type/i18n/fr.po
odoo/addons/product_uom_measure_type/i18n/it.po
odoo/addons/product_uom_measure_type/i18n/product_uom_measure_type.pot
odoo/addons/product_uom_measure_type/models/__init__.py
odoo/addons/product_uom_measure_type/models/product_template.py
odoo/addons/product_uom_measure_type/models/uom_category.py
odoo/addons/product_uom_measure_type/models/uom_uom.py
odoo/addons/product_uom_measure_type/readme/CONTRIBUTORS.md
odoo/addons/product_uom_measure_type/readme/DESCRIPTION.md
odoo/addons/product_uom_measure_type/static/description/icon.png
odoo/addons/product_uom_measure_type/static/description/index.html
odoo/addons/product_uom_measure_type/views/view_product_template.xml
odoo/addons/product_uom_measure_type/views/view_uom_category.xml
odoo/addons/product_uom_measure_type/views/view_uom_uom.xml
odoo_addon_product_uom_measure_type-17.0.1.0.0.2.dist-info/METADATA
odoo_addon_product_uom_measure_type-17.0.1.0.0.2.dist-info/WHEEL
odoo_addon_product_uom_measure_type-17.0.1.0.0.2.dist-info/top_level.txt
odoo_addon_product_uom_measure_type-17.0.1.0.0.2.dist-info/RECORD
